opensourcetest_test_test/__init__.py
opensourcetest_test_test/banner/banner_top.txt
opensourcetest_test_test/builtin/__init__.py
opensourcetest_test_test/builtin/autoParamInjection.py
opensourcetest_test_test/builtin/baseRequest.py
opensourcetest_test_test/builtin/baseUiRunner.py
opensourcetest_test_test/builtin/check.py
opensourcetest_test_test/builtin/exceptions.py
opensourcetest_test_test/builtin/locate.py
opensourcetest_test_test/builtin/models.py
opensourcetest_test_test/builtin/ostDriver.py
opensourcetest_test_test/cli.py
opensourcetest_test_test/common/__init__.py
opensourcetest_test_test/common/comFileOperation.py
opensourcetest_test_test/common/consolelog.py
opensourcetest_test_test/common/dockerOperation.py
opensourcetest_test_test/common/fileOperation.py
opensourcetest_test_test/common/urlOperation.py
opensourcetest_test_test/common/yamlOperation.py
opensourcetest_test_test/httpmodel/.gitignore
opensourcetest_test_test/httpmodel/__init__.py
opensourcetest_test_test/httpmodel/Base/__init__.py
opensourcetest_test_test/httpmodel/Base/baseAssert.py
opensourcetest_test_test/httpmodel/Base/requestEngine.py
opensourcetest_test_test/httpmodel/Common/__init__.py
opensourcetest_test_test/httpmodel/Common/FileOption/__init__.py
opensourcetest_test_test/httpmodel/Common/FileOption/yamlOption.py
opensourcetest_test_test/httpmodel/Common/StringOption/__init__.py
opensourcetest_test_test/httpmodel/Common/StringOption/StringOperate.py
opensourcetest_test_test/httpmodel/Conf/conf.yml
opensourcetest_test_test/httpmodel/conftest.py
opensourcetest_test_test/httpmodel/Parameter/__init__.py
opensourcetest_test_test/httpmodel/Parameter/Login/Login.yaml
opensourcetest_test_test/httpmodel/Parameter/yamlChoice.py
opensourcetest_test_test/httpmodel/pytest.ini
opensourcetest_test_test/httpmodel/README.md
opensourcetest_test_test/httpmodel/requirements.txt
opensourcetest_test_test/httpmodel/run.py
opensourcetest_test_test/httpmodel/TestCases/__init__.py
opensourcetest_test_test-0.3.2.dist-info/entry_points.txt
opensourcetest_test_test-0.3.2.dist-info/LICENSE
opensourcetest_test_test-0.3.2.dist-info/WHEEL
opensourcetest_test_test-0.3.2.dist-info/METADATA
opensourcetest_test_test-0.3.2.dist-info/RECORD
